spyder_memory_profiler/__init__.py
spyder_memory_profiler/memoryprofiler.py
spyder_memory_profiler/data/__init__.py
spyder_memory_profiler/data/images/__init__.py
spyder_memory_profiler/data/images/spyder.memory_profiler.png
spyder_memory_profiler/example/__init__.py
spyder_memory_profiler/example/profiling_test_script.py
spyder_memory_profiler/example/subdir/__init__.py
spyder_memory_profiler/example/subdir/profiling_test_script2.py
spyder_memory_profiler/widgets/__init__.py
spyder_memory_profiler/widgets/memoryprofiler.py
spyder_memory_profiler/widgets/tests/__init__.py
spyder_memory_profiler/widgets/tests/test_memoryprofiler.py
spyder_memory_profiler-0.2.1.dist-info/AUTHORS.md
spyder_memory_profiler-0.2.1.dist-info/LICENSE.txt
spyder_memory_profiler-0.2.1.dist-info/METADATA
spyder_memory_profiler-0.2.1.dist-info/WHEEL
spyder_memory_profiler-0.2.1.dist-info/top_level.txt
spyder_memory_profiler-0.2.1.dist-info/RECORD
