Metadata-Version: 2.1
Name: spyder-memory-profiler
Version: 0.2.1
Summary: Plugin for the Spyder IDE that integrates the Python memory profiler
Home-page: https://github.com/spyder-ide/spyder-memory-profiler
Author: Spyder Project Contributors
Author-email: UNKNOWN
License: MIT
Keywords: Qt PyQt4 PyQt5 PySide spyder plugins spyplugins profiler
Platform: UNKNOWN
Classifier: Development Status :: 4 - Beta
Classifier: Environment :: X11 Applications :: Qt
Classifier: Environment :: Win32 (MS Windows)
Classifier: Intended Audience :: Developers
Classifier: License :: OSI Approved :: MIT License
Classifier: Operating System :: OS Independent
Classifier: Programming Language :: Python :: 2
Classifier: Programming Language :: Python :: 2.7
Classifier: Programming Language :: Python :: 3
Classifier: Programming Language :: Python :: 3.5
Classifier: Programming Language :: Python :: 3.6
Classifier: Topic :: Software Development
Classifier: Topic :: Text Editors :: Integrated Development Environments (IDE)
Requires-Dist: memory-profiler
Requires-Dist: spyder (>=4)
